aioandrewsarnold/__init__.py
aioandrewsarnold/andrewsarnold.py
aioandrewsarnold/exceptions.py
aioandrewsarnold/models.py
aioandrewsarnold/py.typed
aioandrewsarnold-3.0.1.dist-info/LICENSE.md
aioandrewsarnold-3.0.1.dist-info/METADATA
aioandrewsarnold-3.0.1.dist-info/WHEEL
aioandrewsarnold-3.0.1.dist-info/RECORD
