Metadata-Version: 2.1
Name: aioandrewsarnold
Version: 3.0.1
Summary: Asynchronous Python client for Andrews & Arnold Broadband.
Home-page: https://github.com/andrew-codechimp/python-andrews-arnold
License: MIT
Keywords: broadband,api,async,client
Author: Andrew Jackson
Author-email: andrew@codechimp.org
Maintainer: Andrew Jackson
Maintainer-email: andrew@codechimp.org
Requires-Python: >=3.11,<4.0
Classifier: Development Status :: 5 - Production/Stable
Classifier: Framework :: AsyncIO
Classifier: Intended Audience :: Developers
Classifier: License :: OSI Approved :: MIT License
Classifier: Natural Language :: English
Classifier: Programming Language :: Python :: 3
Classifier: Programming Language :: Python :: 3.11
Classifier: Programming Language :: Python :: 3.12
Classifier: Topic :: Software Development :: Libraries :: Python Modules
Requires-Dist: aiohttp (>=3.0.0)
Requires-Dist: mashumaro (>=3.11,<4.0)
Requires-Dist: orjson (>=3.9.0)
Requires-Dist: yarl (>=1.6.0)
Project-URL: Bug Tracker, https://github.com/andrew-codechimp/python-andrews-arnold/issues
Project-URL: Changelog, https://github.com/andrew-codechimp/python-andrews-arnold/releases
Project-URL: Documentation, https://github.com/andrew-codechimp/python-andrews-arnold
Project-URL: Repository, https://github.com/andrew-codechimp/python-andrews-arnold
